expipe_plugin_cinpla/__init__.py
expipe_plugin_cinpla/imports.py
expipe_plugin_cinpla/utils.py
expipe_plugin_cinpla/cli/__init__.py
expipe_plugin_cinpla/cli/main.py
expipe_plugin_cinpla/cli/process.py
expipe_plugin_cinpla/cli/register.py
expipe_plugin_cinpla/cli/utils.py
expipe_plugin_cinpla/nwbutils/__init__.py
expipe_plugin_cinpla/nwbutils/cinplanwbconverter.py
expipe_plugin_cinpla/nwbutils/nwbwidgetsunitviewer.py
expipe_plugin_cinpla/nwbutils/interfaces/__init__.py
expipe_plugin_cinpla/nwbutils/interfaces/openephystrackinginterface.py
expipe_plugin_cinpla/scripts/__init__.py
expipe_plugin_cinpla/scripts/convert_old_project.py
expipe_plugin_cinpla/scripts/curation.py
expipe_plugin_cinpla/scripts/data_processing.py
expipe_plugin_cinpla/scripts/process.py
expipe_plugin_cinpla/scripts/register.py
expipe_plugin_cinpla/scripts/utils.py
expipe_plugin_cinpla/widgets/__init__.py
expipe_plugin_cinpla/widgets/browser.py
expipe_plugin_cinpla/widgets/curation.py
expipe_plugin_cinpla/widgets/process.py
expipe_plugin_cinpla/widgets/register.py
expipe_plugin_cinpla/widgets/utils.py
expipe_plugin_cinpla/widgets/viewer.py
expipe_plugin_cinpla-0.1.5.dist-info/LICENSE
expipe_plugin_cinpla-0.1.5.dist-info/METADATA
expipe_plugin_cinpla-0.1.5.dist-info/WHEEL
expipe_plugin_cinpla-0.1.5.dist-info/top_level.txt
expipe_plugin_cinpla-0.1.5.dist-info/RECORD
