Metadata-Version: 2.1
Name: expipe_plugin_cinpla
Version: 0.1.5
Summary: Expipe plugins for the CINPLA lab.
Author-email: Mikkel Lepperod <mikkel@simula.no>, Alessio Buccino <alessiop.buccino@gmail.com>
Project-URL: homepage, https://github.com/CINPLA/expipe-plugin-cinpla
Project-URL: repository, https://github.com/CINPLA/expipe-plugin-cinpla
Classifier: Programming Language :: Python :: 3
Classifier: License :: OSI Approved :: MIT License
Classifier: Operating System :: OS Independent
Requires-Python: >=3.9
License-File: LICENSE
Requires-Dist: expipe >=0.6.0
Requires-Dist: neuroconv >=0.4.6
Requires-Dist: pyopenephys >=1.2.0
Requires-Dist: spikeinterface[full,widgets] >=0.100.0
Requires-Dist: pynwb >=2.5.0
Requires-Dist: ipywidgets >=8.1.1
Requires-Dist: nwbwidgets >=0.11.3
Requires-Dist: tbb >=2021.11.0
Requires-Dist: pynapple >=0.5.1
Requires-Dist: spython >=0.3.13
Provides-Extra: dev
Requires-Dist: pytest ; extra == 'dev'
Requires-Dist: pytest-cov ; extra == 'dev'
Requires-Dist: pytest-dependency ; extra == 'dev'
Requires-Dist: black ; extra == 'dev'
Provides-Extra: docs
Requires-Dist: sphinx-gallery ; extra == 'docs'
Requires-Dist: sphinx-rtd-theme ; extra == 'docs'
Provides-Extra: test
Requires-Dist: pytest ; extra == 'test'
Requires-Dist: pytest-cov ; extra == 'test'
Requires-Dist: pytest-dependency ; extra == 'test'
Requires-Dist: mountainsort5 ; extra == 'test'
